pyzyconfig/__init__.py
pyzyconfig/saver.py
pyzyconfig-0.0.3.dist-info/METADATA
pyzyconfig-0.0.3.dist-info/WHEEL
pyzyconfig-0.0.3.dist-info/top_level.txt
pyzyconfig-0.0.3.dist-info/RECORD
